{
    "H.264": {

        "CodecID": "avc1, h264"
    },
    "H.265": {
        "CodecID": "hevc, hvc1"
    },
    "MPEG-2": {
        "CodecID": "mpeg2, mp2v"
    },
    "MPEG-4": {
        "CodecID": "mp4v, mp4a"
    },
    "VP8": {
        "CodecID": "vp80"
    },
    "VP9": {
        "CodecID": "vp90"
    },
    "AV1": {
        "CodecID": "av01"
    },
    "DivX": {
        "CodecID": "divx"
    },
    "Xvid": {
        "CodecID": "xvid"
    },
    "MJPEG": {
        "CodecID": "mjpe, mjpeg"
    },
    "ProRes": {
        "CodecID": "apch, apcs, apcn, apco, apch"
    },
    "DNxHD": {
        "CodecID": "dnxh"
    },
    "CineForm": {
        "CodecID": "cfhd"
    },
    "Theora": {
        "CodecID": "theo"
    },
    "RealVideo": {
        "CodecID": "rv30, rv40"
    }
}
